{
  "Nodes": [
    {
      "Rarity": "Uncommon",
      "Ids": [
        "ItemLootTreeNodes.Kitchen.Drinks.NonAlcoholic.Milk",
        "ItemLootTreeNodes.Kitchen.Food.CookingIngredients.Yeast",
        "ItemLootTreeNodes.Kitchen.Food.Dairy.Cheese",
        "ItemLootTreeNodes.Kitchen.Food.Dairy.Butter",
        "ItemLootTreeNodes.Kitchen.Food.Dairy.Richards_Cheese",
        "ItemLootTreeNodes.Kitchen.Food.Dairy.CheesePacked"
      ]
    }
  ],
  "Probability": 11,
  "QuantityMin": 1,
  "QuantityMax": 1,
  "AllowDuplicates": false,
  "ShouldFilterItemsByZone": true,
  "InitialDamage": 18,
  "RandomDamage": 5,
  "InitialUsage": 0,
  "RandomUsage": 0
}